core/__init__.py
core/utility.py
fdk/__init__.py
fdk/fdk.py
fdk_flutter-0.1.dist-info/METADATA
fdk_flutter-0.1.dist-info/WHEEL
fdk_flutter-0.1.dist-info/entry_points.txt
fdk_flutter-0.1.dist-info/top_level.txt
fdk_flutter-0.1.dist-info/RECORD
