Metadata-Version: 2.1
Name: fdk-flutter
Version: 0.1
Requires-Dist: mycolorlogger ==0.8
